data_path.v
module data_path(ldA, ldB, ldP, clrP, decB, eqZ, data_in, clk);
	input ldA, ldB, ldP, clrP, decB;
	input [15:0] data_in;
	input clk;
	output eqZ;

	wire [15:0] X, Y, Z, Bout, Bus;

	assign Bus = data_in;

	PIPO1 reg_A (ldA, Bus, X, clk);
	PIPO2 reg_P (ldP, clrP, Z, Y, clk);
	ADDER Ad (X, Y, Z);
	PIPO3 reg_B (ldB, decB, Bus, Bout, clk);
	COMP comp_B (Bout, eqZ); 
endmodule

module PIPO1 (ldA, Bus, X, clk);
	input ldA, clk;
	input [15:0] Bus;
	output reg [15:0] X;

	always @(posedge clk)
	begin
		if (ldA) X <= Bus;
	end
endmodule 

module PIPO2 (ldP, clrP, Z, Y, clk);
	input ldP, clrP, clk;
	input [15:0] Z;
	output reg [15:0] Y;

	always @(posedge clk)
	begin
		if (clrP) Y <= 16'b0;
		else if (ldP) Y <= Z;
	end
endmodule 

module PIPO3 (ldB, decB, Bus, Bout, clk);
	input ldB, decB, clk;
	input [15:0] Bus;
	output reg [15:0] Bout;

	always @(posedge clk)
	begin
		if (ldB) Bout <= Bus;
		else if (decB) Bout <= Bout - 1;
	end
endmodule 

module ADDER (X, Y, Z);
	input [15:0] X, Y;
	output [15:0] Z;
	assign Z = X + Y;
endmodule

module COMP (Bout, eqZ);
	input [15:0] Bout;
	output eqZ;
	assign eqZ = (Bout == 1);
endmodule

controller.v
module controller (start, done, ldA, ldB, ldP, clrP, decB, eqZ, clk);
	input start, eqZ, clk;
	output reg done, ldA, ldB, ldP, clrP, decB;

	reg [2:0] state;
	parameter S0 = 3'b000, S1 = 3'b001, S2 = 3'b010, S3 = 3'b011, S4 = 3'b100;

	always @(posedge clk)
	begin
		case (state)
			S0: if (start) state <= S1;
			S1: state <= S2;
			S2: state <= S3;
			S3: if (eqZ) state <= S4; 
			S4: state <= S4;
		endcase
	end

	always @(state)
	begin
		case (state)
			S0: begin done = 0; ldA = 0; ldB = 0; ldP = 0; clrP = 0; decB = 0; end
			S1: begin done = 0; ldA = 1; ldB = 0; ldP = 0; clrP = 0; decB = 0; end
			S2: begin done = 0; ldA = 0; ldB = 1; ldP = 0; clrP = 1; decB = 0; end
			S3: begin done = 0; ldA = 0; ldB = 0; ldP = 1; clrP = 0; decB = 1; end
			S4: begin done = 1; ldA = 0; ldB = 0; ldP = 0; clrP = 0; decB = 0; end
			default: begin done = 0; ldA = 0; ldB = 0; ldP = 0; clrP = 0; decB = 0; end
		endcase
	end

endmodule

test_bench.v
module test_bench;
	reg [15:0] data_in;
	reg start, clk;
	wire done;

	wire ldA, ldB, ldP, clrP, decB, eqZ;
	controller controlP(start, done, ldA, ldB, ldP, clrP, decB, eqZ, clk);
	data_path dataP(ldA, ldB, ldP, clrP, decB, eqZ, data_in, clk);

	initial
	begin
		data_in = 16'd0; start = 1'b0; clk = 1'b0; controlP.state = 3'b0;
		#2 start = 1'b1;
		# 100 $finish;
	end

	always #5 clk = ~clk;

	initial
	begin
		#7 data_in = 17;
		#10 data_in = 5;
	end

	initial
	begin
		$monitor($time, " %d %d %d %b", dataP.X, dataP.Y, dataP.Bout, done);
		$dumpfile("mul.vcd"); 
		$dumpvars(0, test_bench);
	end

endmodule

mul.vcd
$date
	Tue Sep  8 18:10:14 2020
$end
$version
	Icarus Verilog
$end
$timescale
	1s
$end
$scope module test_bench $end
$var wire 1 ! ldP $end
$var wire 1 " ldB $end
$var wire 1 # ldA $end
$var wire 1 $ eqZ $end
$var wire 1 % done $end
$var wire 1 & decB $end
$var wire 1 ' clrP $end
$var reg 1 ( clk $end
$var reg 16 ) data_in [15:0] $end
$var reg 1 * start $end
$scope module controlP $end
$var wire 1 ( clk $end
$var wire 1 * start $end
$var wire 1 $ eqZ $end
$var reg 1 ' clrP $end
$var reg 1 & decB $end
$var reg 1 % done $end
$var reg 1 # ldA $end
$var reg 1 " ldB $end
$var reg 1 ! ldP $end
$var reg 3 + state [2:0] $end
$upscope $end
$scope module dataP $end
$var wire 16 , Bus [15:0] $end
$var wire 1 ( clk $end
$var wire 1 ' clrP $end
$var wire 16 - data_in [15:0] $end
$var wire 1 & decB $end
$var wire 1 # ldA $end
$var wire 1 " ldB $end
$var wire 1 ! ldP $end
$var wire 1 $ eqZ $end
$var wire 16 . Z [15:0] $end
$var wire 16 / Y [15:0] $end
$var wire 16 0 X [15:0] $end
$var wire 16 1 Bout [15:0] $end
$scope module Ad $end
$var wire 16 2 Z [15:0] $end
$var wire 16 3 Y [15:0] $end
$var wire 16 4 X [15:0] $end
$upscope $end
$scope module comp_B $end
$var wire 1 $ eqZ $end
$var wire 16 5 Bout [15:0] $end
$upscope $end
$scope module reg_A $end
$var wire 16 6 Bus [15:0] $end
$var wire 1 ( clk $end
$var wire 1 # ldA $end
$var reg 16 7 X [15:0] $end
$upscope $end
$scope module reg_B $end
$var wire 16 8 Bus [15:0] $end
$var wire 1 ( clk $end
$var wire 1 & decB $end
$var wire 1 " ldB $end
$var reg 16 9 Bout [15:0] $end
$upscope $end
$scope module reg_P $end
$var wire 16 : Z [15:0] $end
$var wire 1 ( clk $end
$var wire 1 ' clrP $end
$var wire 1 ! ldP $end
$var reg 16 ; Y [15:0] $end
$upscope $end
$upscope $end
$upscope $end
$enddefinitions $end
#0
$dumpvars
bx ;
bx :
bx 9
b0 8
bx 7
b0 6
bx 5
bx 4
bx 3
bx 2
bx 1
bx 0
bx /
bx .
b0 -
b0 ,
b0 +
0*
b0 )
0(
0'
0&
0%
x$
0#
0"
0!
$end
#2
1*
#5
1#
b1 +
1(
#7
b10001 ,
b10001 6
b10001 8
b10001 )
b10001 -
#10
0(
#15
1'
1"
0#
b10001 0
b10001 4
b10001 7
b10 +
1(
#17
b101 ,
b101 6
b101 8
b101 )
b101 -
#20
0(
#25
1&
0'
1!
0"
b11 +
b10001 .
b10001 2
b10001 :
b0 /
b0 3
b0 ;
0$
b101 1
b101 5
b101 9
1(
#30
0(
#35
b100 1
b100 5
b100 9
b100010 .
b100010 2
b100010 :
b10001 /
b10001 3
b10001 ;
1(
#40
0(
#45
b110011 .
b110011 2
b110011 :
b100010 /
b100010 3
b100010 ;
b11 1
b11 5
b11 9
1(
#50
0(
#55
b10 1
b10 5
b10 9
b1000100 .
b1000100 2
b1000100 :
b110011 /
b110011 3
b110011 ;
1(
#60
0(
#65
b1010101 .
b1010101 2
b1010101 :
b1000100 /
b1000100 3
b1000100 ;
1$
b1 1
b1 5
b1 9
1(
#70
0(
#75
0&
0!
1%
0$
b0 1
b0 5
b0 9
b1100110 .
b1100110 2
b1100110 :
b1010101 /
b1010101 3
b1010101 ;
b100 +
1(
